calvin/__init__.py
calvin/Tools/__init__.py
calvin/Tools/calvindoc.py
calvin/Tools/calvinsysdoc.py
calvin/Tools/csactortest.py
calvin/Tools/cscompiler.py
calvin/Tools/cscontrol.py
calvin/Tools/csmanage.py
calvin/Tools/cspreprocess.py
calvin/Tools/csruntime.py
calvin/Tools/csviz.py
calvin/Tools/csviz_old.py
calvin/Tools/deployer.py
calvin/Tools/log_analyze.py
calvin/Tools/www/__init__.py
calvin/Tools/www/csweb.py
calvin/Tools/www/index.html
calvin/Tools/www/css/bootstrap.min.css
calvin/Tools/www/css/calvin.css
calvin/Tools/www/css/images/ui-bg_flat_0_aaaaaa_40x100.png
calvin/Tools/www/css/images/ui-bg_flat_75_ffffff_40x100.png
calvin/Tools/www/css/images/ui-bg_glass_55_fbf9ee_1x400.png
calvin/Tools/www/css/images/ui-bg_glass_65_ffffff_1x400.png
calvin/Tools/www/css/images/ui-bg_glass_75_dadada_1x400.png
calvin/Tools/www/css/images/ui-bg_glass_75_e6e6e6_1x400.png
calvin/Tools/www/css/images/ui-bg_glass_95_fef1ec_1x400.png
calvin/Tools/www/css/images/ui-bg_highlight-soft_75_cccccc_1x100.png
calvin/Tools/www/css/images/ui-icons_222222_256x240.png
calvin/Tools/www/css/images/ui-icons_2e83ff_256x240.png
calvin/Tools/www/css/images/ui-icons_454545_256x240.png
calvin/Tools/www/css/images/ui-icons_888888_256x240.png
calvin/Tools/www/css/images/ui-icons_cd0a0a_256x240.png
calvin/Tools/www/js/bootstrap.min.js
calvin/Tools/www/js/calvin.js
calvin/Tools/www/js/d3.v3.min.js
calvin/Tools/www/js/dagre-d3.min.js
calvin/Tools/www/lib/jquery.min.js
calvin/Tools/www/lib/spin.js
calvin/actor/__init__.py
calvin/actor/actor.py
calvin/actor/actorport.py
calvin/actorstore/__init__.py
calvin/actorstore/docobject.py
calvin/actorstore/store.py
calvin/actorstore/devactors/__init__.py
calvin/actorstore/devactors/usr/__init__.py
calvin/actorstore/systemactors/__init__.py
calvin/actorstore/systemactors/chart/DynamicHBar.py
calvin/actorstore/systemactors/chart/DynamicLine.py
calvin/actorstore/systemactors/chart/DynamicVBar.py
er_calvin-1.0.1.dist-info/METADATA
er_calvin-1.0.1.dist-info/RECORD
er_calvin-1.0.1.dist-info/WHEEL
er_calvin-1.0.1.dist-info/entry_points.txt
er_calvin-1.0.1.dist-info/top_level.txt
