Metadata-Version: 2.1
Name: er-calvin
Version: 1.0.1
Summary: Calvin is a distributed runtime and development framework for an actor based dataflowprogramming methodology
Home-page: http://github.com/EricssonResearch/calvin-base
Author: Team Calvin @ Ericsson Research
Author-email: labs@ericsson.com
License: Apache Software License
Keywords: iot dataflow actors distributed internet-of-things cloud-computing programming
Platform: any
Classifier: Programming Language :: Python :: 2
Classifier: Programming Language :: Python :: 2.7
Classifier: Development Status :: 4 - Beta
Classifier: License :: OSI Approved :: Apache Software License
Classifier: Operating System :: OS Independent
Classifier: Framework :: Twisted
Classifier: Natural Language :: English
Classifier: Intended Audience :: Developers
Classifier: Topic :: Software Development
Requires-Python: >=2.7
Requires-Dist: colorlog (==2.6.1)
Requires-Dist: rpcudp (==1.0)
Requires-Dist: kademlia (==0.5)
Requires-Dist: ply (==3.8)
Requires-Dist: Twisted (==15.5.0)
Requires-Dist: requests (==2.9.1)
Requires-Dist: infi.traceback (==0.3.12)
Requires-Dist: wrapt (==1.10.2)
Requires-Dist: netifaces (==0.10.4)
Requires-Dist: pyOpenSSL (==17.1.0)
Requires-Dist: cryptography (==1.9.0)
Requires-Dist: passlib (==1.7.0)
Requires-Dist: PyJWT (==1.4.0)
Requires-Dist: service-identity (==17.0.0)
Requires-Dist: ndg-httpsclient (==0.4.2)
Requires-Dist: pyasn1 (>=0.4.2)
Requires-Dist: pystache (==0.5.4)
Requires-Dist: jsonschema (==2.6.0)
Requires-Dist: u-msgpack-python (==2.4.1)
Requires-Dist: cbor (==1.0.0)
